typeffect/__init__.py
typeffect/__main__.py
typeffect/style.py
typeffect/typing.py
typeffect-0.0.1.dist-info/METADATA
typeffect-0.0.1.dist-info/WHEEL
typeffect-0.0.1.dist-info/entry_points.txt
typeffect-0.0.1.dist-info/top_level.txt
typeffect-0.0.1.dist-info/RECORD
