Metadata-Version: 2.1
Name: typeffect
Version: 0.0.1
Summary: UNKNOWN
Home-page: UNKNOWN
Author: Divinemonk
Author-email: <v1b7rc8eb@relay.firefox.com>
License: UNKNOWN
Keywords: python,typeffect,divinemonk,typewriter,cli,typing,console,typewriter effect
Platform: UNKNOWN
Classifier: Programming Language :: Python :: 3
Classifier: License :: OSI Approved :: MIT License
Requires-Dist: rich
